{
  "organization_level-10101001": "갓 세워진 중요시설입니다. 여기서 명령을 총괄하여 모든 부서는 이를 중심으로 돌아갑니다.",
  "organization_level-10101002": "갓 세워진 중요시설입니다. 여기서 명령을 총괄하여 모든 부서는 이를 중심으로 돌아갑니다.",
  "organization_level-10101003": "이젠 없어선 안 될 핵심 시설. 이곳을 중심으로 구성된 지휘망이 대국을 좌우합니다.",
  "organization_level-10102001": "엘리트 인형을 모으고자 하는 전선 부대. 그리폰의 주요 전력입니다.",
  "organization_level-10102002": "엘리트 인형을 모으고자 하는 전선 부대. 그리폰의 주요 전력입니다.",
  "organization_level-10102003": "엘리트 인형을 모으고자 하는 전선 부대. 그리폰의 주요 전력입니다.",
  "organization_level-10102004": "엘리트 인형을 모으고자 하는 전선 부대. 그리폰의 주요 전력입니다.",
  "organization_level-10102005": "엘리트 인형을 모으고자 하는 전선 부대. 어느 정도 형태를 갖추었고, 용감한 의지를 가졌습니다.",
  "organization_level-10102006": "엘리트 인형을 모으고자 하는 전선 부대. 어느 정도 형태를 갖추었고, 용감한 의지를 가졌습니다.",
  "organization_level-10102007": "엘리트 인형을 모으고자 하는 전선 부대. 어느 정도 형태를 갖추었고, 용감한 의지를 가졌습니다.",
  "organization_level-10102008": "엘리트 인형을 모으고자 하는 전선 부대. 어느 정도 형태를 갖추었고, 용감한 의지를 가졌습니다.",
  "organization_level-10102009": "엘리트 인형을 모으고자 하는 전선 부대. 이미 칼날을 드러내어 환수의 부리처럼 모든 것을 깨부수고 승리를 거머쥘 것입니다.",
  "organization_level-10102010": "엘리트 인형을 모으고자 하는 전선 부대. 이미 칼날을 드러내어 환수의 부리처럼 모든 것을 깨부수고 승리를 거머쥘 것입니다.",
  "organization_level-10102011": "엘리트 인형을 모으고자 하는 전선 부대. 이미 칼날을 드러내어 환수의 부리처럼 모든 것을 깨부수고 승리를 거머쥘 것입니다.",
  "organization_level-10102012": "엘리트 인형을 모으고자 하는 전선 부대. 이미 칼날을 드러내어 환수의 부리처럼 모든 것을 깨부수고 승리를 거머쥘 것입니다.",
  "organization_level-10102013": "엘리트 인형을 모으고자 하는 전선 부대. 이미 칼날을 드러내어 환수의 부리처럼 모든 것을 깨부수고 승리를 거머쥘 것입니다.",
  "organization_level-10102014": "엘리트 인형을 모으고자 하는 전선 부대. 이미 칼날을 드러내어 환수의 부리처럼 모든 것을 깨부수고 승리를 거머쥘 것입니다.",
  "organization_level-10102015": "엘리트 인형을 모으고자 하는 전선 부대. 이미 칼날을 드러내어 환수의 부리처럼 모든 것을 깨부수고 승리를 거머쥘 것입니다.",
  "organization_level-10102016": "엘리트 인형을 모으고자 하는 전선 부대. 이미 칼날을 드러내어 환수의 부리처럼 모든 것을 깨부수고 승리를 거머쥘 것입니다.",
  "organization_level-10102017": "엘리트 인형을 모으고자 하는 전선 부대. 이미 칼날을 드러내어 환수의 부리처럼 모든 것을 깨부수고 승리를 거머쥘 것입니다.",
  "organization_level-10103001": "중견 인형을 모으고자 하는 전략 부대. 그리폰의 기본적인 예비 전력입니다.",
  "organization_level-10103002": "중견 인형을 모으고자 하는 전략 부대. 그리폰의 기본적인 예비 전력입니다.",
  "organization_level-10103003": "중견 인형을 모으고자 하는 전략 부대. 그리폰의 기본적인 예비 전력입니다.",
  "organization_level-10103004": "중견 인형을 모으고자 하는 전략 부대. 그리폰의 기본적인 예비 전력입니다.",
  "organization_level-10103005": "중견 인형을 모으고자 하는 전략 부대. 어느 정도 형태를 갖추었고, 적극적으로 나아갈 의지를 가졌습니다.",
  "organization_level-10103006": "중견 인형을 모으고자 하는 전략 부대. 어느 정도 형태를 갖추었고, 적극적으로 나아갈 의지를 가졌습니다.",
  "organization_level-10103007": "중견 인형을 모으고자 하는 전략 부대. 어느 정도 형태를 갖추었고, 적극적으로 나아갈 의지를 가졌습니다.",
  "organization_level-10103008": "중견 인형을 모으고자 하는 전략 부대. 어느 정도 형태를 갖추었고, 적극적으로 나아갈 의지를 가졌습니다.",
  "organization_level-10103009": "중견 인형을 모으고자 하는 전략 부대. 이미 칼날을 드러내어 환수의 깃털처럼 온몸을 감싸고 먼지를 털어냅니다.",
  "organization_level-10103010": "중견 인형을 모으고자 하는 전략 부대. 이미 칼날을 드러내어 환수의 깃털처럼 온몸을 감싸고 먼지를 털어냅니다.",
  "organization_level-10103011": "중견 인형을 모으고자 하는 전략 부대. 이미 칼날을 드러내어 환수의 깃털처럼 온몸을 감싸고 먼지를 털어냅니다.",
  "organization_level-10103012": "중견 인형을 모으고자 하는 전략 부대. 이미 칼날을 드러내어 환수의 깃털처럼 온몸을 감싸고 먼지를 털어냅니다.",
  "organization_level-10103013": "중견 인형을 모으고자 하는 전략 부대. 이미 칼날을 드러내어 환수의 깃털처럼 온몸을 감싸고 먼지를 털어냅니다.",
  "organization_level-10103014": "중견 인형을 모으고자 하는 전략 부대. 이미 칼날을 드러내어 환수의 깃털처럼 온몸을 감싸고 먼지를 털어냅니다.",
  "organization_level-10103015": "중견 인형을 모으고자 하는 전략 부대. 이미 칼날을 드러내어 환수의 깃털처럼 온몸을 감싸고 먼지를 털어냅니다.",
  "organization_level-10103016": "중견 인형을 모으고자 하는 전략 부대. 이미 칼날을 드러내어 환수의 깃털처럼 온몸을 감싸고 먼지를 털어냅니다.",
  "organization_level-10104001": "예리한 인형을 모으고자 하는 조사 부대. 그리폰이 미지의 영역을 탐색하는 힘입니다.",
  "organization_level-10104002": "예리한 인형을 모으고자 하는 조사 부대. 그리폰이 미지의 영역을 탐색하는 힘입니다.",
  "organization_level-10104003": "예리한 인형을 모으고자 하는 조사 부대. 그리폰이 미지의 영역을 탐색하는 힘입니다.",
  "organization_level-10104004": "예리한 인형을 모으고자 하는 조사 부대. 그리폰이 미지의 영역을 탐색하는 힘입니다.",
  "organization_level-10104005": "예리한 인형을 모으고자 하는 조사 부대.어느 정도 형태를 갖추었고, 지식을 갈망하는 의지를 가졌습니다.",
  "organization_level-10104006": "예리한 인형을 모으고자 하는 조사 부대.어느 정도 형태를 갖추었고, 지식을 갈망하는 의지를 가졌습니다.",
  "organization_level-10104007": "예리한 인형을 모으고자 하는 조사 부대.어느 정도 형태를 갖추었고, 지식을 갈망하는 의지를 가졌습니다.",
  "organization_level-10104008": "예리한 인형을 모으고자 하는 조사 부대.어느 정도 형태를 갖추었고, 지식을 갈망하는 의지를 가졌습니다.",
  "organization_level-10104009": "예리한 인형을 모으고자 하는 조사 부대.이미 칼날을 드러내어 환수의 눈처럼 천리밖에서도 적을 뚜렷하게 관측할 수 있습니다.",
  "organization_level-10104010": "예리한 인형을 모으고자 하는 조사 부대.이미 칼날을 드러내어 환수의 눈처럼 천리밖에서도 적을 뚜렷하게 관측할 수 있습니다.",
  "organization_level-10104011": "예리한 인형을 모으고자 하는 조사 부대.이미 칼날을 드러내어 환수의 눈처럼 천리밖에서도 적을 뚜렷하게 관측할 수 있습니다.",
  "organization_level-10104012": "예리한 인형을 모으고자 하는 조사 부대.이미 칼날을 드러내어 환수의 눈처럼 천리밖에서도 적을 뚜렷하게 관측할 수 있습니다.",
  "organization_level-10104013": "예리한 인형을 모으고자 하는 조사 부대.이미 칼날을 드러내어 환수의 눈처럼 천리밖에서도 적을 뚜렷하게 관측할 수 있습니다.",
  "organization_level-10104014": "예리한 인형을 모으고자 하는 조사 부대.이미 칼날을 드러내어 환수의 눈처럼 천리밖에서도 적을 뚜렷하게 관측할 수 있습니다.",
  "organization_level-10104015": "예리한 인형을 모으고자 하는 조사 부대.이미 칼날을 드러내어 환수의 눈처럼 천리밖에서도 적을 뚜렷하게 관측할 수 있습니다.",
  "organization_level-10105001": "믿음직한 인형을 모으고자 하는 지원 부대. 그리폰의 주요 보조 역량입니다.",
  "organization_level-10105002": "믿음직한 인형을 모으고자 하는 지원 부대. 그리폰의 주요 보조 역량입니다.",
  "organization_level-10105003": "믿음직한 인형을 모으고자 하는 지원 부대. 그리폰의 주요 보조 역량입니다.",
  "organization_level-10105004": "믿음직한 인형을 모으고자 하는 지원 부대. 그리폰의 주요 보조 역량입니다.",
  "organization_level-10105005": "믿음직한 인형을 모으고자 하는 지원 부대. 어느 정도 형태를 갖추었고, 굴하지 않는 의지를 가졌습니다.",
  "organization_level-10105006": "믿음직한 인형을 모으고자 하는 지원 부대. 어느 정도 형태를 갖추었고, 굴하지 않는 의지를 가졌습니다.",
  "organization_level-10105007": "믿음직한 인형을 모으고자 하는 지원 부대. 어느 정도 형태를 갖추었고, 굴하지 않는 의지를 가졌습니다.",
  "organization_level-10105008": "믿음직한 인형을 모으고자 하는 지원 부대. 어느 정도 형태를 갖추었고, 굴하지 않는 의지를 가졌습니다.",
  "organization_level-10105009": "믿음직한 인형을 모으고자 하는 지원 부대. 이미 칼날을 드러내어 환수의 발톱처럼 다가오는 적을 붙잡습니다.",
  "organization_level-10105010": "믿음직한 인형을 모으고자 하는 지원 부대. 이미 칼날을 드러내어 환수의 발톱처럼 다가오는 적을 붙잡습니다.",
  "organization_level-10105011": "믿음직한 인형을 모으고자 하는 지원 부대. 이미 칼날을 드러내어 환수의 발톱처럼 다가오는 적을 붙잡습니다.",
  "organization_level-10106001": "강역한 도움을 모으고자 하는 곳. 일상 훈련과 실험 연구를 진행할 수 있습니다.",
  "organization_level-10106002": "강역한 도움을 모으고자 하는 곳. 일상 훈련과 실험 연구를 진행할 수 있습니다.",
  "organization_level-10106003": "강역한 도움을 모으고자 하는 곳. 일상 훈련과 실험 연구를 진행할 수 있습니다.",
  "organization_level-10106004": "강역한 도움을 모으고자 하는 곳. 일상 훈련과 실험 연구를 진행할 수 있습니다.",
  "organization_level-10106005": "강역한 도움을 모으고자 하는 곳. 더욱 포괄적인 훈련과 기술 개발이 가능합니다.",
  "organization_level-10106006": "강역한 도움을 모으고자 하는 곳. 더욱 포괄적인 훈련과 기술 개발이 가능합니다.",
  "organization_level-10106007": "강역한 도움을 모으고자 하는 곳. 더욱 포괄적인 훈련과 기술 개발이 가능합니다.",
  "organization_level-10106008": "강역한 도움을 모으고자 하는 곳. 더욱 포괄적인 훈련과 기술 개발이 가능합니다.",
  "organization_level-10106009": "강역한 도움을 모으고자 하는 곳. 성숙된 기술로 검토하고 검증하여 이곳의 구성원이 그리폰에 있어 똑같이 중요한 힘이 되게 합니다.",
  "organization_level-10107001": "착실한 인형을 모으고자 하는 근무팀. 그리폰의 주요 기반 역량입니다.",
  "organization_level-10107002": "착실한 인형을 모으고자 하는 근무팀. 그리폰의 주요 기반 역량입니다.",
  "organization_level-10107003": "착실한 인형을 모으고자 하는 근무팀. 그리폰의 주요 기반 역량입니다.",
  "organization_level-10107004": "착실한 인형을 모으고자 하는 근무팀. 그리폰의 주요 기반 역량입니다.",
  "organization_level-10107005": "착실한 인형을 모으고자 하는 근무팀. 어느 정도 형태를 갖추었고, 근면한 의지를 가졌습니다.",
  "organization_level-10107006": "착실한 인형을 모으고자 하는 근무팀. 어느 정도 형태를 갖추었고, 근면한 의지를 가졌습니다.",
  "organization_level-10107007": "착실한 인형을 모으고자 하는 근무팀. 어느 정도 형태를 갖추었고, 근면한 의지를 가졌습니다.",
  "organization_level-10107008": "착실한 인형을 모으고자 하는 근무팀. 어느 정도 형태를 갖추었고, 근면한 의지를 가졌습니다.",
  "organization_level-10107009": "착실한 인형을 모으고자 하는 근무팀. 이미 칼날을 드러내어 환수의 날개처럼 공기를 박차고 수많은 고비를 넘게 합니다.",
  "organization_level-10107010": "착실한 인형을 모으고자 하는 근무팀. 이미 칼날을 드러내어 환수의 날개처럼 공기를 박차고 수많은 고비를 넘게 합니다.",
  "organization_level-10107011": "착실한 인형을 모으고자 하는 근무팀. 이미 칼날을 드러내어 환수의 날개처럼 공기를 박차고 수많은 고비를 넘게 합니다.",
  "organization_level-10107012": "착실한 인형을 모으고자 하는 근무팀. 이미 칼날을 드러내어 환수의 날개처럼 공기를 박차고 수많은 고비를 넘게 합니다.",
  "organization_level-10107013": "착실한 인형을 모으고자 하는 근무팀. 이미 칼날을 드러내어 환수의 날개처럼 공기를 박차고 수많은 고비를 넘게 합니다.",
  "organization_level-10107014": "착실한 인형을 모으고자 하는 근무팀. 이미 칼날을 드러내어 환수의 날개처럼 공기를 박차고 수많은 고비를 넘게 합니다.",
  "organization_level-10107015": "착실한 인형을 모으고자 하는 근무팀. 이미 칼날을 드러내어 환수의 날개처럼 공기를 박차고 수많은 고비를 넘게 합니다.",
  "organization_level-10107016": "착실한 인형을 모으고자 하는 근무팀. 이미 칼날을 드러내어 환수의 날개처럼 공기를 박차고 수많은 고비를 넘게 합니다.",
  "organization_level-10108001": "인형들이 심신을 푸는 곳. 간단한 오락 활동이 가능합니다.",
  "organization_level-10108002": "인형들이 심신을 푸는 곳. 간단한 오락 활동이 가능합니다.",
  "organization_level-10108003": "인형들이 심신을 푸는 곳. 간단한 오락 활동이 가능합니다.",
  "organization_level-10108004": "인형들이 심신을 푸는 곳. 간단한 오락 활동이 가능합니다.",
  "organization_level-10108005": "인형들이 심신을 푸는 곳. 각종 파티나 명절 이벤트를 조직할 수 있습니다.",
  "organization_level-10108006": "인형들이 심신을 푸는 곳. 각종 파티나 명절 이벤트를 조직할 수 있습니다.",
  "organization_level-10108007": "인형들이 심신을 푸는 곳. 각종 파티나 명절 이벤트를 조직할 수 있습니다.",
  "organization_level-10108008": "인형들이 심신을 푸는 곳. 각종 파티나 명절 이벤트를 조직할 수 있습니다.",
  "organization_level-10108009": "인형들이 심신을 푸는 곳. 각종 성대한 파티나 명절 잔치를 개최할 수 있습니다.",
  "organization_level-10108010": "인형들이 심신을 푸는 곳. 각종 성대한 파티나 명절 잔치를 개최할 수 있습니다.",
  "organization_level-10108011": "인형들이 심신을 푸는 곳. 각종 성대한 파티나 명절 잔치를 개최할 수 있습니다."
}