[
  {
    "background": {
      "id": 9
    },
    "screenEffect": "dark1"
  },
  {
    "background": {
      "id": 99
    },
    "screenEffect": "spark",
    "sound": {
      "bgm": "BGM_Sad",
      "se1": "Gunfight"
    },
    "text": "..."
  },
  {
    "text": "한 동안 필사적으로 저항한 끝에, SOP2는 결국 군의 병력에게 포위당했다."
  },
  {
    "characters": [
      {
        "name": "NPC-Yegor",
        "face": 3
      }
    ],
    "speaker": {
      "index": 0,
      "name": "군용인형"
    },
    "text": "목표를 확보, 다음 지시 대기 중.+... 양호."
  },
  {
    "characters": [
      {
        "name": "M4 SOPMOD II"
      }
    ],
    "text": "여기까지인가..."
  },
  {
    "sound": {
      "se1": "Select"
    },
    "text": "군용 인형이 무기를 들었다."
  },
  {
    "characters": [
      {
        "name": "M4 SOPMOD II"
      }
    ],
    "text": "헤헷...+그래도... 할만큼 한 거겠지...+내가 할 수 있는 것들을 다 해서..."
  },
  {
    "screenEffect": "closeSpark",
    "sound": {
      "se1": "MachineGunBurst"
    },
    "text": "타탕!"
  },
  {
    "background": {
      "id": 9
    },
    "screenEffect": "dark2",
    "characters": [
      {
        "name": ""
      }
    ],
    "speaker": {
      "index": 0,
      "name": "M4 SOPMOD II"
    },
    "text": "여기까지... 왔으니까..+그러니까..."
  },
  {
    "sound": {
      "se1": "Gunfight"
    },
    "text": "타타탕!"
  },
  {
    "characters": [
      {
        "name": "<Speaker></Speaker>"
      }
    ],
    "speaker": {
      "index": 0
    },
    "text": "그 무엇도 남지 않았고, 그 무엇도 변하지 않았다.+총소리와 함께 SOP2의 발자국은 핏자국 없는 전장에 영원히 끊기게 되었다."
  },
  {
    "screenEffect": "dark2",
    "characters": [
      {
        "name": "<Speaker></Speaker>"
      }
    ],
    "speaker": {
      "index": 0
    },
    "text": "……END？"
  }
]